{
  "manifestVersion": "3.2",
  "proxies": [
    {
      "address": "0x5d7f98F3B41fdda52FC5Faf2eE009bE6591c01a3",
      "txHash": "0xe986ca2a1b1a8abf31ca2e2bb265b87c4316fe53a53fc0e2d3312054d55c2a50",
      "kind": "uups"
    }
  ],
  "impls": {
    "8b6a57ea214201e1aa09c8ef76505ce1a5b29b97270d8d0986621f6ae18f56ce": {
      "address": "0x5a9da959948AdeEE81B988d1d06574e839540C86",
      "txHash": "0xa6c0314d5b4cb7ecd2c99605f552dee25dfdce75e4a305803ea33fcbb5951d13",
      "layout": {
        "solcVersion": "0.8.28",
        "storage": [
          {
            "label": "_names",
            "offset": 0,
            "slot": "0",
            "type": "t_mapping(t_uint256,t_string_storage)",
            "contract": "PeachpitV02",
            "src": "contracts/PeachpitV02.sol:25"
          }
        ],
        "types": {
          "t_address": {
            "label": "address",
            "numberOfBytes": "20"
          },
          "t_bool": {
            "label": "bool",
            "numberOfBytes": "1"
          },
          "t_mapping(t_address,t_bool)": {
            "label": "mapping(address => bool)",
            "numberOfBytes": "32"
          },
          "t_mapping(t_address,t_mapping(t_address,t_bool))": {
            "label": "mapping(address => mapping(address => bool))",
            "numberOfBytes": "32"
          },
          "t_mapping(t_address,t_uint256)": {
            "label": "mapping(address => uint256)",
            "numberOfBytes": "32"
          },
          "t_mapping(t_uint256,t_address)": {
            "label": "mapping(uint256 => address)",
            "numberOfBytes": "32"
          },
          "t_string_storage": {
            "label": "string",
            "numberOfBytes": "32"
          },
          "t_struct(ERC721Storage)240_storage": {
            "label": "struct ERC721Upgradeable.ERC721Storage",
            "members": [
              {
                "label": "_name",
                "type": "t_string_storage",
                "offset": 0,
                "slot": "0"
              },
              {
                "label": "_symbol",
                "type": "t_string_storage",
                "offset": 0,
                "slot": "1"
              },
              {
                "label": "_owners",
                "type": "t_mapping(t_uint256,t_address)",
                "offset": 0,
                "slot": "2"
              },
              {
                "label": "_balances",
                "type": "t_mapping(t_address,t_uint256)",
                "offset": 0,
                "slot": "3"
              },
              {
                "label": "_tokenApprovals",
                "type": "t_mapping(t_uint256,t_address)",
                "offset": 0,
                "slot": "4"
              },
              {
                "label": "_operatorApprovals",
                "type": "t_mapping(t_address,t_mapping(t_address,t_bool))",
                "offset": 0,
                "slot": "5"
              }
            ],
            "numberOfBytes": "192"
          },
          "t_struct(InitializableStorage)73_storage": {
            "label": "struct Initializable.InitializableStorage",
            "members": [
              {
                "label": "_initialized",
                "type": "t_uint64",
                "offset": 0,
                "slot": "0"
              },
              {
                "label": "_initializing",
                "type": "t_bool",
                "offset": 8,
                "slot": "0"
              }
            ],
            "numberOfBytes": "32"
          },
          "t_struct(OwnableStorage)13_storage": {
            "label": "struct OwnableUpgradeable.OwnableStorage",
            "members": [
              {
                "label": "_owner",
                "type": "t_address",
                "offset": 0,
                "slot": "0"
              }
            ],
            "numberOfBytes": "32"
          },
          "t_uint256": {
            "label": "uint256",
            "numberOfBytes": "32"
          },
          "t_uint64": {
            "label": "uint64",
            "numberOfBytes": "8"
          },
          "t_mapping(t_uint256,t_string_storage)": {
            "label": "mapping(uint256 => string)",
            "numberOfBytes": "32"
          }
        },
        "namespaces": {
          "erc7201:openzeppelin.storage.Ownable": [
            {
              "contract": "OwnableUpgradeable",
              "label": "_owner",
              "type": "t_address",
              "src": "@openzeppelin/contracts-upgradeable/access/OwnableUpgradeable.sol:24",
              "offset": 0,
              "slot": "0"
            }
          ],
          "erc7201:openzeppelin.storage.ERC721": [
            {
              "contract": "ERC721Upgradeable",
              "label": "_name",
              "type": "t_string_storage",
              "src": "@openzeppelin/contracts-upgradeable/token/ERC721/ERC721Upgradeable.sol:27",
              "offset": 0,
              "slot": "0"
            },
            {
              "contract": "ERC721Upgradeable",
              "label": "_symbol",
              "type": "t_string_storage",
              "src": "@openzeppelin/contracts-upgradeable/token/ERC721/ERC721Upgradeable.sol:30",
              "offset": 0,
              "slot": "1"
            },
            {
              "contract": "ERC721Upgradeable",
              "label": "_owners",
              "type": "t_mapping(t_uint256,t_address)",
              "src": "@openzeppelin/contracts-upgradeable/token/ERC721/ERC721Upgradeable.sol:32",
              "offset": 0,
              "slot": "2"
            },
            {
              "contract": "ERC721Upgradeable",
              "label": "_balances",
              "type": "t_mapping(t_address,t_uint256)",
              "src": "@openzeppelin/contracts-upgradeable/token/ERC721/ERC721Upgradeable.sol:34",
              "offset": 0,
              "slot": "3"
            },
            {
              "contract": "ERC721Upgradeable",
              "label": "_tokenApprovals",
              "type": "t_mapping(t_uint256,t_address)",
              "src": "@openzeppelin/contracts-upgradeable/token/ERC721/ERC721Upgradeable.sol:36",
              "offset": 0,
              "slot": "4"
            },
            {
              "contract": "ERC721Upgradeable",
              "label": "_operatorApprovals",
              "type": "t_mapping(t_address,t_mapping(t_address,t_bool))",
              "src": "@openzeppelin/contracts-upgradeable/token/ERC721/ERC721Upgradeable.sol:38",
              "offset": 0,
              "slot": "5"
            }
          ],
          "erc7201:openzeppelin.storage.Initializable": [
            {
              "contract": "Initializable",
              "label": "_initialized",
              "type": "t_uint64",
              "src": "@openzeppelin/contracts-upgradeable/proxy/utils/Initializable.sol:69",
              "offset": 0,
              "slot": "0"
            },
            {
              "contract": "Initializable",
              "label": "_initializing",
              "type": "t_bool",
              "src": "@openzeppelin/contracts-upgradeable/proxy/utils/Initializable.sol:73",
              "offset": 8,
              "slot": "0"
            }
          ]
        }
      }
    }
  }
}
